htms/HTMSLParser.py
htms/__init__.py
htms/__main__.py
htms/config.toml
htms/constants.py
htms/example_html/astro_pagination.html
htms/example_html/bc_1.html
htms/example_html/bc_nested.html
htms/example_html/freecodecamp_title.html
htms/example_html/json_api_example.html
htms/example_html/multiple_requests_bbc.html
htms/example_html/muz_news.html
htms/example_html/national_geographic.html
htms/example_html/phys_1.html
htms/example_html/phys_2_request_list.html
htms/example_html/phys_3_multiple.html
htms/example_html/table_example.html
htms/examples/__main__.py
htms/logging.py
htms/tags/ExportTag.py
htms/tags/ExportTagBase.py
htms/tags/ItemTag.py
htms/tags/ListTag.py
htms/tags/RequestListTag.py
htms/tags/RequestTag.py
htms/tags/TagBase.py
htms/tags/constants.py
htms/utils.py
htms-0.1.10.dist-info/METADATA
htms-0.1.10.dist-info/WHEEL
htms-0.1.10.dist-info/RECORD
