Metadata-Version: 2.1
Name: htms
Version: 0.1.10
Summary: A Python web scraping library using HTML
Home-page: https://github.com/BowangLan/htms
License: MIT
Keywords: web scraping,HTML
Author: BowangLan
Author-email: bwldev85@uw.edu
Requires-Python: >=3.11,<4.0
Classifier: Environment :: Console
Classifier: Intended Audience :: Developers
Classifier: License :: OSI Approved :: MIT License
Classifier: Programming Language :: Python :: 3
Classifier: Programming Language :: Python :: 3.11
Classifier: Topic :: Internet :: WWW/HTTP
Classifier: Topic :: Software Development :: Libraries :: Application Frameworks
Classifier: Topic :: Software Development :: Libraries :: Python Modules
Classifier: Topic :: Text Processing :: Markup :: HTML
Requires-Dist: lxml (>=5.3.0,<6.0.0)
Requires-Dist: requests (>=2.32.3,<3.0.0)
Requires-Dist: rich (>=13.8.0,<14.0.0)
Project-URL: Repository, https://github.com/BowangLan/htms
